wallet/__init__.py
wallet/utils.py
wallet/wallet_adrs.py
WalletPy-0.1.1.dist-info/METADATA
WalletPy-0.1.1.dist-info/WHEEL
WalletPy-0.1.1.dist-info/top_level.txt
WalletPy-0.1.1.dist-info/RECORD
